rtl/fir_transposed.v
module fir_transposed (
    input  wire                 clk,
    input  wire                 reset,
    input  wire signed [15:0]   x_in,
    output reg  signed [35:0]   y_out
);

    // ==========================================================
    // 1. KHAI BÁO HỆ SỐ (Đảo ngược: Đi lùi từ H15 về H0)
    // ==========================================================
    localparam signed [15:0] H15 = -16'sd114;
    localparam signed [15:0] H14 = -16'sd159;
    localparam signed [15:0] H13 = -16'sd139;
    localparam signed [15:0] H12 =  16'sd291;
    localparam signed [15:0] H11 =  16'sd1450;
    localparam signed [15:0] H10 =  16'sd3284;
    localparam signed [15:0] H9  =  16'sd5246;
    localparam signed [15:0] H8  =  16'sd6524;
    localparam signed [15:0] H7  =  16'sd6524;
    localparam signed [15:0] H6  =  16'sd5246;
    localparam signed [15:0] H5  =  16'sd3284;
    localparam signed [15:0] H4  =  16'sd1450;
    localparam signed [15:0] H3  =  16'sd291;
    localparam signed [15:0] H2  = -16'sd139;
    localparam signed [15:0] H1  = -16'sd159;
    localparam signed [15:0] H0  = -16'sd114;

    // ==========================================================
    // 2. TẠO CÁC THANH GHI CỘNG DỒN (Accumulators / Delay Registers)
    // ==========================================================
    // Cần 15 thanh ghi trung gian (từ acc_0 đến acc_14) đóng vai trò Z^-1
    reg signed [35:0] acc [0:14];
    integer i;

    // ==========================================================
    // 3. KHỐI TÍNH TOÁN TRANSPOSED (Tuyến đường dích dắc)
    // ==========================================================
    always @(posedge clk or posedge reset) begin
        if (reset) begin
            for (i = 0; i < 15; i = i + 1) begin
                acc[i] <= 36'd0;
            end
            y_out <= 36'd0;
        end else begin
            // Trạm đầu tiên bên trái (Chỉ có nhân, rót thẳng vào Z^-1)
            acc[0] <= x_in * H15;

            // Các trạm ở giữa: [Kết quả Z^-1 trạm trước] + [Nhân dội từ trên xuống]
            acc[1]  <= acc[0]  + (x_in * H14);
            acc[2]  <= acc[1]  + (x_in * H13);
            acc[3]  <= acc[2]  + (x_in * H12);
            acc[4]  <= acc[3]  + (x_in * H11);
            acc[5]  <= acc[4]  + (x_in * H10);
            acc[6]  <= acc[5]  + (x_in * H9);
            acc[7]  <= acc[6]  + (x_in * H8);
            acc[8]  <= acc[7]  + (x_in * H7);
            acc[9]  <= acc[8]  + (x_in * H6);
            acc[10] <= acc[9]  + (x_in * H5);
            acc[11] <= acc[10] + (x_in * H4);
            acc[12] <= acc[11] + (x_in * H3);
            acc[13] <= acc[12] + (x_in * H2);
            acc[14] <= acc[13] + (x_in * H1);

            // Trạm cuối cùng bên phải (Xuất thẳng ra y_out)
            y_out   <= acc[14] + (x_in * H0);
        end
    end

endmodule

rtl/fir_direct.v
module fir_direct (
    input  wire                 clk,
    input  wire                 reset,
    input  wire signed [15:0]   x_in,    
    output reg  signed [35:0]   y_out    
);

    // ==========================================================
    // 1. KHAI BÁO HỆ SỐ BỘ LỌC (Đã lấy từ file coeffs.txt)
    // ==========================================================
    localparam signed [15:0] H0  = -16'sd114;
    localparam signed [15:0] H1  = -16'sd159;
    localparam signed [15:0] H2  = -16'sd139;
    localparam signed [15:0] H3  =  16'sd291;
    localparam signed [15:0] H4  =  16'sd1450;
    localparam signed [15:0] H5  =  16'sd3284;
    localparam signed [15:0] H6  =  16'sd5246;
    localparam signed [15:0] H7  =  16'sd6524;
    localparam signed [15:0] H8  =  16'sd6524;
    localparam signed [15:0] H9  =  16'sd5246;
    localparam signed [15:0] H10 =  16'sd3284;
    localparam signed [15:0] H11 =  16'sd1450;
    localparam signed [15:0] H12 =  16'sd291;
    localparam signed [15:0] H13 = -16'sd139;
    localparam signed [15:0] H14 = -16'sd159;
    localparam signed [15:0] H15 = -16'sd114;

    // ==========================================================
    // 2. MẠNG THANH GHI DỊCH (Shift Registers / Delay Line)
    // ==========================================================
    reg signed [15:0] delay_line [0:15];
    integer i;

    // ==========================================================
    // 3. KHỐI TÍNH TOÁN (Đồng bộ theo xung nhịp Clock)
    // ==========================================================
    always @(posedge clk or posedge reset) begin
        if (reset) begin
            for (i = 0; i < 16; i = i + 1) begin
                delay_line[i] <= 16'd0;
            end
            y_out <= 36'd0;
        end else begin
            // A. DỊCH DỮ LIỆU
            delay_line[0] <= x_in;
            for (i = 1; i < 16; i = i + 1) begin
                delay_line[i] <= delay_line[i-1];
            end

            // B. NHÂN VÀ CỘNG DỒN (MAC)
            y_out <= (delay_line[0]  * H0)  +
                     (delay_line[1]  * H1)  +
                     (delay_line[2]  * H2)  +
                     (delay_line[3]  * H3)  +
                     (delay_line[4]  * H4)  +
                     (delay_line[5]  * H5)  +
                     (delay_line[6]  * H6)  +
                     (delay_line[7]  * H7)  +
                     (delay_line[8]  * H8)  +
                     (delay_line[9]  * H9)  +
                     (delay_line[10] * H10) +
                     (delay_line[11] * H11) +
                     (delay_line[12] * H12) +
                     (delay_line[13] * H13) +
                     (delay_line[14] * H14) +
                     (delay_line[15] * H15);
        end
    end

endmodule

tb/tb_fir.v
`timescale 1ns / 1ps

module tb_fir;

    // 1. KHAI BÁO TÍN HIỆU
    reg clk;
    reg reset;
    reg signed [15:0] x_in;
    
    wire signed [35:0] y_out_dir;
    wire signed [35:0] y_out_trans;

    // 2. BIẾN QUẢN LÝ FILE
    integer in_file;
    integer out_file_dir;
    integer out_file_trans;
    integer scan_status;

    // 3. NHÚNG MẠCH DIRECT FORM VÀO TESTBENCH
    fir_direct dut_direct (
        .clk(clk),
        .reset(reset),
        .x_in(x_in),
        .y_out(y_out_dir)
    );

    // 4. NHÚNG MẠCH TRANSPOSED FORM VÀO TESTBENCH
    fir_transposed dut_transposed (
        .clk(clk),
        .reset(reset),
        .x_in(x_in),
        .y_out(y_out_trans)
    );

    // 5. TẠO XUNG ĐỒNG HỒ CLOCK (Tần số 100MHz)
    initial begin
        clk = 0;
        forever #5 clk = ~clk; 
    end

    // BONUS: XUẤT FILE VCD ĐỂ ĐO CÔNG SUẤT ĐỘNG (QUARTUS)
    initial begin
        $dumpfile("fir_power_v1.vcd");
        $dumpvars(0, tb_fir); 
    end

    // 6. KỊCH BẢN CHẠY CHÍNH
    initial begin
        // Mở file đọc dữ liệu đầu vào (cùng thư mục)
        in_file = $fopen("input_data.txt", "r");
        
        // Tạo file mới để ghi kết quả đầu ra
        out_file_dir   = $fopen("output_direct.txt", "w");
        out_file_trans = $fopen("output_transposed.txt", "w");

        if (in_file == 0) begin
            $display("LỖI: Không tìm thấy file input_data.txt!");
            $finish;
        end

        // Khởi tạo trạng thái ban đầu (Reset mạch)
        reset = 1;
        x_in = 0;
        #20; 
        reset = 0; // Tắt reset, mạch bắt đầu chạy
        #10;

        // Vòng lặp: Đọc từng dòng file input_data.txt nhét vào mạch
        while (!$feof(in_file)) begin
            scan_status = $fscanf(in_file, "%d\n", x_in);
            @(posedge clk); // Đợi 1 nhịp đồng hồ
        end

        // Đợi thêm 16 nhịp Clock để toàn bộ dữ liệu trôi hết ra khỏi mạch
        repeat(16) @(posedge clk);

        // Đóng toàn bộ file và kết thúc mô phỏng
        $fclose(in_file);
        $fclose(out_file_dir);
        $fclose(out_file_trans);
        $display("MO PHONG HOAN TAT THANH CONG!");
        $finish;
    end

    // 7. GHI NHẬN KẾT QUẢ ĐẦU RA VÀO FILE TXT
    // Dùng sườn âm (negedge) để lấy mẫu tín hiệu đã ổn định
    always @(negedge clk) begin
        if (!reset) begin
            $fdisplay(out_file_dir, "%d", y_out_dir);
            $fdisplay(out_file_trans, "%d", y_out_trans);
        end
    end

endmodule

sim/fir_power.vcd
$date
	Thu Jun 18 23:00:23 2026
$end
$version
	ModelSim Version 2020.1
$end
$timescale
	1ps
$end

$scope module tb_fir $end
$var reg 1 ! clk $end
$var reg 1 " reset $end
$var reg 16 # x_in [15:0] $end
$var wire 1 $ y_out_dir [35] $end
$var wire 1 % y_out_dir [34] $end
$var wire 1 & y_out_dir [33] $end
$var wire 1 ' y_out_dir [32] $end
$var wire 1 ( y_out_dir [31] $end
$var wire 1 ) y_out_dir [30] $end
$var wire 1 * y_out_dir [29] $end
$var wire 1 + y_out_dir [28] $end
$var wire 1 , y_out_dir [27] $end
$var wire 1 - y_out_dir [26] $end
$var wire 1 . y_out_dir [25] $end
$var wire 1 / y_out_dir [24] $end
$var wire 1 0 y_out_dir [23] $end
$var wire 1 1 y_out_dir [22] $end
$var wire 1 2 y_out_dir [21] $end
$var wire 1 3 y_out_dir [20] $end
$var wire 1 4 y_out_dir [19] $end
$var wire 1 5 y_out_dir [18] $end
$var wire 1 6 y_out_dir [17] $end
$var wire 1 7 y_out_dir [16] $end
$var wire 1 8 y_out_dir [15] $end
$var wire 1 9 y_out_dir [14] $end
$var wire 1 : y_out_dir [13] $end
$var wire 1 ; y_out_dir [12] $end
$var wire 1 < y_out_dir [11] $end
$var wire 1 = y_out_dir [10] $end
$var wire 1 > y_out_dir [9] $end
$var wire 1 ? y_out_dir [8] $end
$var wire 1 @ y_out_dir [7] $end
$var wire 1 A y_out_dir [6] $end
$var wire 1 B y_out_dir [5] $end
$var wire 1 C y_out_dir [4] $end
$var wire 1 D y_out_dir [3] $end
$var wire 1 E y_out_dir [2] $end
$var wire 1 F y_out_dir [1] $end
$var wire 1 G y_out_dir [0] $end
$var wire 1 H y_out_trans [35] $end
$var wire 1 I y_out_trans [34] $end
$var wire 1 J y_out_trans [33] $end
$var wire 1 K y_out_trans [32] $end
$var wire 1 L y_out_trans [31] $end
$var wire 1 M y_out_trans [30] $end
$var wire 1 N y_out_trans [29] $end
$var wire 1 O y_out_trans [28] $end
$var wire 1 P y_out_trans [27] $end
$var wire 1 Q y_out_trans [26] $end
$var wire 1 R y_out_trans [25] $end
$var wire 1 S y_out_trans [24] $end
$var wire 1 T y_out_trans [23] $end
$var wire 1 U y_out_trans [22] $end
$var wire 1 V y_out_trans [21] $end
$var wire 1 W y_out_trans [20] $end
$var wire 1 X y_out_trans [19] $end
$var wire 1 Y y_out_trans [18] $end
$var wire 1 Z y_out_trans [17] $end
$var wire 1 [ y_out_trans [16] $end
$var wire 1 \ y_out_trans [15] $end
$var wire 1 ] y_out_trans [14] $end
$var wire 1 ^ y_out_trans [13] $end
$var wire 1 _ y_out_trans [12] $end
$var wire 1 ` y_out_trans [11] $end
$var wire 1 a y_out_trans [10] $end
$var wire 1 b y_out_trans [9] $end
$var wire 1 c y_out_trans [8] $end
$var wire 1 d y_out_trans [7] $end
$var wire 1 e y_out_trans [6] $end
$var wire 1 f y_out_trans [5] $end
$var wire 1 g y_out_trans [4] $end
$var wire 1 h y_out_trans [3] $end
$var wire 1 i y_out_trans [2] $end
$var wire 1 j y_out_trans [1] $end
$var wire 1 k y_out_trans [0] $end
$var integer 32 l in_file $end
$var integer 32 m out_file_dir $end
$var integer 32 n out_file_trans $end
$var integer 32 o scan_status $end

$scope module dut_direct $end
$var parameter 16 p H0 $end
$var parameter 16 q H1 $end
$var parameter 16 r H2 $end
$var parameter 16 s H3 $end
$var parameter 16 t H4 $end
$var parameter 16 u H5 $end
$var parameter 16 v H6 $end
$var parameter 16 w H7 $end
$var parameter 16 x H8 $end
$var parameter 16 y H9 $end
$var parameter 16 z H10 $end
$var parameter 16 { H11 $end
$var parameter 16 | H12 $end
$var parameter 16 } H13 $end
$var parameter 16 ~ H14 $end
$var parameter 16 !! H15 $end
$var wire 1 "! clk $end
$var wire 1 #! reset $end
$var wire 1 $! x_in [15] $end
$var wire 1 %! x_in [14] $end
$var wire 1 &! x_in [13] $end
$var wire 1 '! x_in [12] $end
$var wire 1 (! x_in [11] $end
$var wire 1 )! x_in [10] $end
$var wire 1 *! x_in [9] $end
$var wire 1 +! x_in [8] $end
$var wire 1 ,! x_in [7] $end
$var wire 1 -! x_in [6] $end
$var wire 1 .! x_in [5] $end
$var wire 1 /! x_in [4] $end
$var wire 1 0! x_in [3] $end
$var wire 1 1! x_in [2] $end
$var wire 1 2! x_in [1] $end
$var wire 1 3! x_in [0] $end
$var reg 36 4! y_out [35:0] $end
$var integer 32 5! i $end
$upscope $end

$scope module dut_transposed $end
$var parameter 16 6! H15 $end
$var parameter 16 7! H14 $end
$var parameter 16 8! H13 $end
$var parameter 16 9! H12 $end
$var parameter 16 :! H11 $end
$var parameter 16 ;! H10 $end
$var parameter 16 <! H9 $end
$var parameter 16 =! H8 $end
$var parameter 16 >! H7 $end
$var parameter 16 ?! H6 $end
$var parameter 16 @! H5 $end
$var parameter 16 A! H4 $end
$var parameter 16 B! H3 $end
$var parameter 16 C! H2 $end
$var parameter 16 D! H1 $end
$var parameter 16 E! H0 $end
$var wire 1 F! clk $end
$var wire 1 G! reset $end
$var wire 1 H! x_in [15] $end
$var wire 1 I! x_in [14] $end
$var wire 1 J! x_in [13] $end
$var wire 1 K! x_in [12] $end
$var wire 1 L! x_in [11] $end
$var wire 1 M! x_in [10] $end
$var wire 1 N! x_in [9] $end
$var wire 1 O! x_in [8] $end
$var wire 1 P! x_in [7] $end
$var wire 1 Q! x_in [6] $end
$var wire 1 R! x_in [5] $end
$var wire 1 S! x_in [4] $end
$var wire 1 T! x_in [3] $end
$var wire 1 U! x_in [2] $end
$var wire 1 V! x_in [1] $end
$var wire 1 W! x_in [0] $end
$var reg 36 X! y_out [35:0] $end
$var integer 32 Y! i $end
$upscope $end
$upscope $end
$enddefinitions $end
#0
$dumpvars
0!
1"
b0 #
b0 4!
b0 X!
b1111111110001110 p
b1111111101100001 q
b1111111101110101 r
b100100011 s
b10110101010 t
b110011010100 u
b1010001111110 v
b1100101111100 w
b1100101111100 x
b1010001111110 y
b110011010100 z
b10110101010 {
b100100011 |
b1111111101110101 }
b1111111101100001 ~
b1111111110001110 !!
b1111111110001110 6!
b1111111101100001 7!
b1111111101110101 8!
b100100011 9!
b10110101010 :!
b110011010100 ;!
b1010001111110 <!
b1100101111100 =!
b1100101111100 >!
b1010001111110 ?!
b110011010100 @!
b10110101010 A!
b100100011 B!
b1111111101110101 C!
b1111111101100001 D!
b1111111110001110 E!
b10000000000000000000000000000011 l
b10000000000000000000000000000100 m
b10000000000000000000000000000101 n
bx o
b10000 5!
b1111 Y!
0G
0F
0E
0D
0C
0B
0A
0@
0?
0>
0=
0<
0;
0:
09
08
07
06
05
04
03
02
01
00
0/
0.
0-
0,
0+
0*
0)
0(
0'
0&
0%
0$
0k
0j
0i
0h
0g
0f
0e
0d
0c
0b
0a
0`
0_
0^
0]
0\
0[
0Z
0Y
0X
0W
0V
0U
0T
0S
0R
0Q
0P
0O
0N
0M
0L
0K
0J
0I
0H
0W!
0V!
0U!
0T!
0S!
0R!
0Q!
0P!
0O!
0N!
0M!
0L!
0K!
0J!
0I!
0H!
1G!
0F!
03!
02!
01!
00!
0/!
0.!
0-!
0,!
0+!
0*!
0)!
0(!
0'!
0&!
0%!
0$!
1#!
0"!
$end
#5000
1!
1"!
1F!
b0 Y!
b1 Y!
b10 Y!
b11 Y!
b100 Y!
b101 Y!
b110 Y!
b111 Y!
b1000 Y!
b1001 Y!
b1010 Y!
b1011 Y!
b1100 Y!
b1101 Y!
b1110 Y!
b1111 Y!
b0 5!
b1 5!
b10 5!
b11 5!
b100 5!
b101 5!
b110 5!
b111 5!
b1000 5!
b1001 5!
b1010 5!
b1011 5!
b1100 5!
b1101 5!
b1110 5!
b1111 5!
b10000 5!
#10000
0!
0"!
0F!
#15000
1!
1"!
1F!
b0 Y!
b1 Y!
b10 Y!
b11 Y!
b100 Y!
b101 Y!
b110 Y!
b111 Y!
b1000 Y!
b1001 Y!
b1010 Y!
b1011 Y!
b1100 Y!
b1101 Y!
b1110 Y!
b1111 Y!
b0 5!
b1 5!
b10 5!
b11 5!
b100 5!
b101 5!
b110 5!
b111 5!
b1000 5!
b1001 5!
b1010 5!
b1011 5!
b1100 5!
b1101 5!
b1110 5!
b1111 5!
b10000 5!
#20000
0"
0!
0#!
0G!
0"!
0F!
#25000
1!
1"!
1F!
b1 5!
b10 5!
b11 5!
b100 5!
b101 5!
b110 5!
b111 5!
b1000 5!
b1001 5!
b1010 5!
b1011 5!
b1100 5!
b1101 5!
b1110 5!
b1111 5!
b10000 5!
#30000
b1 o
0!
0"!
0F!
#35000
1!
1"!
1F!
b1 5!
b10 5!
b11 5!
b100 5!
b101 5!
b110 5!
b111 5!
b1000 5!
b1001 5!
b1010 5!
b1011 5!
b1100 5!
b1101 5!
b1110 5!
b1111 5!
b10000 5!
b100010011100011 #
1W!
1V!
1R!
1Q!
1P!
1M!
1I!
13!
12!
1.!
1-!
1,!
1)!
1%!
#40000
0!
0"!
0F!
#45000
1!
1"!
1F!
b1 5!
b10 5!
b11 5!
b100 5!
b101 5!
b110 5!
b111 5!
b1000 5!
b1001 5!
b1010 5!
b1011 5!
b1100 5!
b1101 5!
b1110 5!
b1111 5!
b10000 5!
b1110101001001100 #
0W!
0V!
1U!
1T!
0R!
0P!
1N!
0M!
1L!
1J!
1H!
03!
02!
11!
10!
0.!
0,!
1*!
0)!
1(!
1&!
1$!
b111111111111111000010101001011101010 X!
1j
1h
1f
1e
1d
1b
1_
1]
1[
1V
1U
1T
1S
1R
1Q
1P
1O
1N
1M
1L
1K
1J
1I
1H
#50000
0!
0"!
0F!
#55000
1!
1"!
1F!
b1 5!
b10 5!
b11 5!
b100 5!
b101 5!
b110 5!
b111 5!
b1000 5!
b1001 5!
b1010 5!
b1011 5!
b1100 5!
b1101 5!
b1110 5!
b1111 5!
b10000 5!
b1111000111110001 #
1W!
0U!
0T!
1S!
1R!
1P!
1O!
0N!
0L!
1K!
13!
01!
00!
1/!
1.!
1,!
1+!
0*!
0(!
1'!
b111111111111110111101110000100101011 X!
b111111111111111000010101001011101010 4!
1F
1D
1B
1A
1@
1>
1;
19
17
12
11
10
1/
1.
1-
1,
1+
1*
1)
1(
1'
1&
1%
1$
1k
0e
0d
1c
0b
0_
1^
1\
0[
1Z
1Y
1X
1W
0V
#60000
0!
0"!
0F!
#65000
1!
1"!
1F!
b1 5!
b10 5!
b11 5!
b100 5!
b101 5!
b110 5!
b111 5!
b1000 5!
b1001 5!
b1010 5!
b1011 5!
b1100 5!
b1101 5!
b1110 5!
b1111 5!
b10000 5!
b101101110110010 #
0W!
1V!
0Q!
1N!
1L!
0J!
0H!
03!
12!
0-!
1*!
1(!
0&!
0$!
b111111111111111011100101011000111001 X!
b111111111111110111101110000100101011 4!
1G
0A
0@
1?
0>
0;
1:
18
07
16
15
14
13
02
0j
1g
0c
1b
1a
1_
0^
0\
0W
1V
#70000
0!
0"!
0F!
#75000
1!
1"!
1F!
b1 5!
b10 5!
b11 5!
b100 5!
b101 5!
b110 5!
b111 5!
b1000 5!
b1001 5!
b1010 5!
b1011 5!
b1100 5!
b1101 5!
b1110 5!
b1111 5!
b10000 5!
b10010110011110 #
1U!
1T!
0R!
0N!
1M!
0L!
0K!
1J!
0I!
11!
10!
0.!
0*!
1)!
0(!
0'!
1&!
0%!
b1110011111110011010010 X!
b111111111111111011100101011000111001 4!
0F
1C
0?
1>
1=
1;
0:
08
03
12
0k
1j
0h
0f
1e
1d
0b
1`
1^
1\
1[
0Z
0Y
1W
0U
0T
0S
0R
0Q
0P
0O
0N
0M
0L
0K
0J
0I
0H
#80000
0!
0"!
0F!
#85000
1!
1"!
1F!
b1 5!
b10 5!
b11 5!
b100 5!
b101 5!
b110 5!
b111 5!
b1000 5!
b1001 5!
b1010 5!
b1011 5!
b1100 5!
b1101 5!
b1110 5!
b1111 5!
b10000 5!
b1110111011110010 #
0U!
0T!
1R!
1Q!
0O!
1N!
1L!
1I!
1H!
01!
00!
1.!
1-!
0+!
1*!
1(!
1%!
1$!
b1001010110111000001011101 X!
b1110011111110011010010 4!
0G
1F
0D
0B
1A
1@
0>
1<
1:
18
17
06
05
13
01
00
0/
0.
0-
0,
0+
0*
0)
0(
0'
0&
0%
0$
1k
0j
1i
1h
0d
0a
0`
0\
1Z
0W
1S
#90000
0!
0"!
0F!
#95000
1!
1"!
1F!
b1 5!
b10 5!
b11 5!
b100 5!
b101 5!
b110 5!
b111 5!
b1000 5!
b1001 5!
b1010 5!
b1011 5!
b1100 5!
b1101 5!
b1110 5!
b1111 5!
b10000 5!
b101011011101110 #
1U!
1T!
0S!
0L!
1K!
0J!
0H!
11!
10!
0/!
0(!
1'!
0&!
0$!
b10101001110011100011011011 X!
b1001010110111000001011101 4!
1G
0F
1E
1D
0@
0=
0<
08
16
03
1/
1j
0i
1d
1`
0]
1Y
0X
1T
0S
1R
#100000
0!
0"!
0F!
#105000
1!
1"!
1F!
b1 5!
b10 5!
b11 5!
b100 5!
b101 5!
b110 5!
b111 5!
b1000 5!
b1001 5!
b1010 5!
b1011 5!
b1100 5!
b1101 5!
b1110 5!
b1111 5!
b10000 5!
b101101110100111 #
1W!
0T!
0Q!
1O!
0M!
1L!
13!
00!
0-!
1+!
0)!
1(!
b100010101010100100111110110 X!
b10101001110011100011011011 4!
1F
0E
1@
1<
09
15
04
10
0/
1.
0k
1i
0h
1f
1c
0_
0^
1]
0Z
1W
0V
1U
0T
0R
1Q
#110000
0!
0"!
0F!
#115000
1!
1"!
1F!
b1 5!
b10 5!
b11 5!
b100 5!
b101 5!
b110 5!
b111 5!
b1000 5!
b1001 5!
b1010 5!
b1011 5!
b1100 5!
b1101 5!
b1110 5!
b1111 5!
b10000 5!
b1111110100001011 #
0U!
1T!
0R!
0P!
0N!
1M!
1J!
1H!
01!
10!
0.!
0,!
0*!
1)!
1&!
1$!
b110010001110000011100101000 X!
b100010101010100100111110110 4!
0G
1E
0D
1B
1?
0;
0:
19
06
13
02
11
00
0.
1-
0j
0i
1h
0g
0e
0d
1b
1a
0`
0]
1Z
0W
1R
#120000
0!
0"!
0F!
#125000
1!
1"!
1F!
b1 5!
b10 5!
b11 5!
b100 5!
b101 5!
b110 5!
b111 5!
b1000 5!
b1001 5!
b1010 5!
b1011 5!
b1100 5!
b1101 5!
b1110 5!
b1111 5!
b10000 5!
b11110011011110 #
0W!
1U!
1S!
1Q!
1P!
0O!
0I!
0H!
03!
11!
1/!
1-!
1,!
0+!
0%!
0$!
b1000100001011000000011110011 X!
b110010001110000011100101000 4!
0F
0E
1D
0C
0A
0@
1>
1=
0<
09
16
03
1.
1k
1j
0h
1g
1e
1d
0c
0b
0a
1\
0Z
0U
1T
0R
0Q
1P
#130000
0!
0"!
0F!
#135000
1!
1"!
1F!
b1 5!
b10 5!
b11 5!
b100 5!
b101 5!
b110 5!
b111 5!
b1000 5!
b1001 5!
b1010 5!
b1011 5!
b1100 5!
b1101 5!
b1110 5!
b1111 5!
b10000 5!
b111101110111011 #
1W!
0U!
1R!
0Q!
1O!
1N!
0M!
1I!
13!
01!
1.!
0-!
1+!
1*!
0)!
1%!
b1010111001010000110110011010 X!
b1000100001011000000011110011 4!
1G
1F
0D
1C
1A
1@
0?
0>
0=
18
06
01
10
0.
0-
1,
0k
1h
0f
0e
1c
1a
1`
0\
1V
1U
1R
#140000
0!
0"!
0F!
#145000
1!
1"!
1F!
b1 5!
b10 5!
b11 5!
b100 5!
b101 5!
b110 5!
b111 5!
b1000 5!
b1001 5!
b1010 5!
b1011 5!
b1100 5!
b1101 5!
b1110 5!
b1111 5!
b10000 5!
b1101001000001 #
0V!
0T!
0S!
0R!
1Q!
0P!
0O!
0J!
0I!
02!
00!
0/!
0.!
1-!
0,!
0+!
0&!
0%!
b1101100100101100111001000100 X!
b1010111001010000110110011010 4!
0G
1D
0B
0A
1?
1=
1<
08
12
11
1.
0j
1i
0h
0g
1e
0d
0c
1b
1]
1\
0[
1Z
0Y
1W
0V
0U
1S
0R
1Q
#150000
0!
0"!
0F!
#155000
1!
1"!
1F!
b1 5!
b10 5!
b11 5!
b100 5!
b101 5!
b110 5!
b111 5!
b1000 5!
b1001 5!
b1010 5!
b1011 5!
b1100 5!
b1101 5!
b1110 5!
b1111 5!
b10000 5!
b10000101101101111010100000110 X!
b1101100100101100111001000100 4!
0F
1E
0D
0C
1A
0@
0?
1>
19
18
07
16
05
13
02
01
1/
0.
1-
1j
0e
1c
0b
0`
1_
1^
1Y
1V
0S
0Q
0P
1O
#160000
0!
0"!
0F!
#165000
1!
1"!
1F!
b1 5!
b10 5!
b11 5!
b100 5!
b101 5!
b110 5!
b111 5!
b1000 5!
b1001 5!
b1010 5!
b1011 5!
b1100 5!
b1101 5!
b1110 5!
b1111 5!
b10000 5!
b111101110111011 #
1V!
1T!
1S!
1R!
0Q!
1P!
1O!
1J!
1I!
12!
10!
1/!
1.!
0-!
1,!
1+!
1&!
1%!
b10011111001000111010110101111 X!
b10000101101101111010100000110 4!
1F
0A
1?
0>
0<
1;
1:
15
12
0/
0-
0,
1+
1k
1h
1f
1d
0\
0Z
0W
1U
1S
1R
#170000
0!
0"!
0F!
#175000
1!
1"!
1F!
b1 5!
b10 5!
b11 5!
b100 5!
b101 5!
b110 5!
b111 5!
b1000 5!
b1001 5!
b1010 5!
b1011 5!
b1100 5!
b1101 5!
b1110 5!
b1111 5!
b10000 5!
b11110011011110 #
0W!
1U!
0R!
1Q!
0O!
0N!
1M!
0I!
03!
11!
0.!
1-!
0+!
0*!
1)!
0%!
b10110110000100001111100110100 X!
b10011111001000111010110101111 4!
1G
1D
1B
1@
08
06
03
11
1/
1.
0k
0j
0h
1g
0d
1b
1`
0^
0]
1Z
0Y
0V
0S
1Q
#180000
0!
0"!
0F!
#185000
1!
1"!
1F!
b1 5!
b10 5!
b11 5!
b100 5!
b101 5!
b110 5!
b111 5!
b1000 5!
b1001 5!
b1010 5!
b1011 5!
b1100 5!
b1101 5!
b1110 5!
b1111 5!
b10000 5!
b1111110100001011 #
1W!
0U!
0S!
0Q!
0P!
1O!
1I!
1H!
13!
01!
0/!
0-!
0,!
1+!
1%!
1$!
b11001010110010010110100001101 X!
b10110110000100001111100110100 4!
0G
0F
0D
1C
0@
1>
1<
0:
09
16
05
02
0/
1-
1k
1h
0g
0f
0b
0_
1^
1[
0Z
1X
1W
0T
1S
0R
0Q
1P
#190000
0!
0"!
0F!
#195000
1!
1"!
1F!
b1 5!
b10 5!
b11 5!
b100 5!
b101 5!
b110 5!
b111 5!
b1000 5!
b1001 5!
b1010 5!
b1011 5!
b1100 5!
b1101 5!
b1110 5!
b1111 5!
b10000 5!
b101101110100111 #
1U!
0T!
1R!
1P!
1N!
0M!
0J!
0H!
11!
00!
1.!
1,!
1*!
0)!
0&!
0$!
b11011100000000001011010111101 X!
b11001010110010010110100001101 4!
1G
1D
0C
0B
0>
0;
1:
17
06
14
13
00
1/
0.
0-
1,
1g
1f
1d
0c
1b
0`
1_
0^
0[
0X
0W
0U
1T
1R
#200000
0!
0"!
0F!
#205000
1!
1"!
1F!
b1 5!
b10 5!
b11 5!
b100 5!
b101 5!
b110 5!
b111 5!
b1000 5!
b1001 5!
b1010 5!
b1011 5!
b1100 5!
b1101 5!
b1110 5!
b1111 5!
b10000 5!
b101011011101110 #
0W!
1T!
1Q!
0O!
1M!
0L!
03!
10!
1-!
0+!
1)!
0(!
b11101001100010111111100100011 X!
b11011100000000001011010111101 4!
1C
1B
1@
0?
1>
0<
1;
0:
07
04
03
01
10
1.
1j
0i
0h
0g
0d
1c
1`
1^
1]
1[
1W
1V
0T
0R
1Q
#210000
0!
0"!
0F!
#215000
1!
1"!
1F!
b1 5!
b10 5!
b11 5!
b100 5!
b101 5!
b110 5!
b111 5!
b1000 5!
b1001 5!
b1010 5!
b1011 5!
b1100 5!
b1101 5!
b1110 5!
b1111 5!
b10000 5!
b1110111011110010 #
0U!
0T!
1S!
1L!
0K!
1J!
1H!
01!
00!
1/!
1(!
0'!
1&!
1$!
b11110010111000001111111110110 X!
b11101001100010111111100100011 4!
1F
0E
0D
0C
0@
1?
1<
1:
19
17
13
12
00
0.
1-
0k
1i
1g
1e
1d
0^
0]
0[
1Y
1X
0V
1U
0S
1R
#220000
0!
0"!
0F!
#225000
1!
1"!
1F!
b1 5!
b10 5!
b11 5!
b100 5!
b101 5!
b110 5!
b111 5!
b1000 5!
b1001 5!
b1010 5!
b1011 5!
b1100 5!
b1101 5!
b1110 5!
b1111 5!
b10000 5!
b10010110011110 #
1U!
1T!
0R!
0Q!
1O!
0N!
0L!
0I!
0H!
11!
10!
0.!
0-!
1+!
0*!
0(!
0%!
0$!
b11111000111010001011110011000 X!
b11110010111000001111111110110 4!
0G
1E
1C
1A
1@
0:
09
07
15
14
02
11
0/
1.
0j
0i
1h
0f
0e
0`
1[
0U
1S
#230000
0!
0"!
0F!
#235000
1!
1"!
1F!
b1 5!
b10 5!
b11 5!
b100 5!
b101 5!
b110 5!
b111 5!
b1000 5!
b1001 5!
b1010 5!
b1011 5!
b1100 5!
b1101 5!
b1110 5!
b1111 5!
b10000 5!
b101101110110010 #
0U!
0T!
1R!
1N!
0M!
1L!
1K!
0J!
1I!
01!
00!
1.!
1*!
0)!
1(!
1'!
0&!
1%!
b11111011001101110101100111010 X!
b11111000111010001011110011000 4!
0F
0E
1D
0B
0A
0<
17
01
1/
1j
1f
0d
0a
1`
0_
1^
1]
1\
0[
1Z
0X
0W
1V
1U
#240000
0!
0"!
0F!
#245000
1!
1"!
1F!
b1 5!
b10 5!
b11 5!
b100 5!
b101 5!
b110 5!
b111 5!
b1000 5!
b1001 5!
b1010 5!
b1011 5!
b1100 5!
b1101 5!
b1110 5!
b1111 5!
b10000 5!
b1111000111110001 #
1W!
0V!
1Q!
0N!
0L!
1J!
1H!
13!
02!
1-!
0*!
0(!
1&!
1$!
b11111000111010001011110011000 X!
b11111011001101110101100111010 4!
1F
1B
0@
0=
1<
0;
1:
19
18
07
16
04
03
12
11
0j
0f
1d
1a
0`
1_
0^
0]
0\
1[
0Z
1X
1W
0V
0U
#250000
0!
0"!
0F!
